Workbook

Sheet Summary
A1: VeerNXT Social - Campaign Plan & Costing
A2: Draft for review. Audience: Indian Ex-Service Men (ESM), families and employers. Channels: LinkedIn, X, Instagram, Facebook.
A4: At a glance
A5: Start date | B5: =Assumptions!B4 -> 46307
A6: End date (last post) | B6: =MAX(Schedule!G5:G68) -> 46361
A7: Duration (weeks) | B7: =MAX(Schedule!B5:B68) -> 8
A8: Content items (themes) | B8: =Costing!C5 -> 16
A9: Total posts across all platforms | B9: =Costing!C6 -> 64
A10: Posts per week (all platforms) | B10: =Cadence!K9 -> 8
A11: Reduction vs posting daily on every platform | B11: =Cadence!B14 -> 0.71428571
A13: Cadence per platform (posts per week)
A14: LinkedIn | B14: =Cadence!K5 -> 2
A15: X | B15: =Cadence!K6 -> 2
A16: Instagram | B16: =Cadence!K7 -> 2
A17: Facebook | B17: =Cadence!K8 -> 2
A19: Estimated AI generation cost (INR)
B20: Low | C20: Expected | D20: High
A21: Total campaign | B21: =Costing!E14 -> 48.636 | C21: =Costing!F14 -> 78.165 | D21: =Costing!G14 -> 165.208
A22: Per content item | B22: =Costing!E16 -> 3.03975 | C22: =Costing!F16 -> 4.8853125 | D22: =Costing!G16 -> 10.3255
A23: Per post | B23: =Costing!E17 -> 0.7599375 | C23: =Costing!F17 -> 1.2213281 | D23: =Costing!G17 -> 2.581375
A25: For approval / to confirm
A26: 1. Audience wording: the website is written largely for Agniveers, but the social brand rules exclude that word. Decide whether social posts stay ESM/veteran-only.
A27: 2. Themes, order and pillars (Themes sheet) - approve, replace or reorder.
A28: 3. Claims to verify before posting (last column of the Themes sheet): "Government Approved", SEBI-compliant, NISM-certified, "500+ exams", community and veteran counts.
A29: 4. Features not yet live or fully stocked: Legal Aid Cell ("demonstration"), WhatsApp alerts, Rewards catalogue, app-store listings.
A30: 5. Start date, posting days and IST posting times; whether all four platforms are needed.
A31: 6. Publishing method: currently Mock / Manual; native platform integration and any scheduler are not yet priced.
A32: 7. Not costed: paid promotion, staff time, hosting, GST and bank charges.
A33: 8. All posts follow brand rules: "Ex-Service Men (ESM)" terminology, no invented facts, statistics or testimonials; every post is reviewed and approved before publishing.
A35: Cost figures are estimates; see Costing and Assumptions sheets for basis and sources.

Sheet Themes
A1: Campaign Themes
A2: Umbrella theme: "Your Second Mission". A journey from awareness to joining. Built from what the VeerNXT site and app actually do. Edit the blue cells; the Schedule updates.
A4: Item # | B4: Week | C4: Phase | D4: Pillar | E4: Theme | F4: Key message (draft) | G4: Where it comes from | H4: Verify before posting
A5: 1 | B5: 1 | C5: Awareness | D5: P0 The Second Mission | E5: Your second mission begins here | F5: VeerNXT is a veteran-led platform helping Ex-Service Men (ESM) move into civilian and government careers: jobs, study tools, finance and support in one place. | G5: Site hero and "Why VeerNXT" copy; stakeholder talking points. | H5: "Government of India Approved" (older hero) vs "Aligned" (landing) - use neither until confirmed. "First Defence Reintegration EdTech" needs proof.
A6: 2 | B6: 1 | C6: Awareness | D6: P1 Your Skills, Translated | E6: Your service skills are civilian skills | F6: Trade, rank and education translate into a civilian skill profile. Discipline and leadership are only part of the story. | G6: Profiling flow; stakeholder talking points, section 3. | H6: None - no statistics used.
A7: 3 | B7: 2 | C7: Discover | D7: P1 Your Skills, Translated | E7: Thirty seconds to your profile | F7: Tell us your education, goals and preferred locations. VeerNXT recommends your best-fit exams and next steps. | G7: How VeerNXT Works: Profile Scan and Mission Assignment steps. | H7: Confirm the "30 seconds" timing against the current profiling flow.
A8: 4 | B8: 2 | C8: Discover | D8: P1 Your Skills, Translated | E8: Your Veer Score: know where you stand | F8: One clear picture of your strengths and your best-fit exam matches, so you know where to start. | G8: Stakeholder talking points; Dashboard "Top Exam Matches". | H8: Describe the score in words only; do not quote score numbers.
A9: 5 | B9: 3 | C9: Discover | D9: P2 Every Opportunity, One Place | E9: Every new job, one place | F9: New government jobs from 10+ portals in one app, with closed listings removed daily. | G9: Stakeholder talking points, section 2 (jobs scraper). | H9: Confirm current portal count and daily refresh before quoting.
A10: 6 | B10: 3 | C10: Discover | D10: P2 Every Opportunity, One Place | E10: Never miss a benefit meant for you | F10: Ex-servicemen quotas, age relaxations and bonus marks are highlighted on each job, so you do not miss what is built for you. | G10: Stakeholder talking points, section 2; eligibility engine. | H10: Keep to ESM benefits; agree wording with the content team so it is accurate per notification.
A11: 7 | B11: 4 | C11: Prepare | D11: P3 Prepare to Win | E11: From target job to study plan | F11: Pick a career such as Bank Officer, Railways or State Police and get its syllabus, previous-year papers, guides and quizzes. | G11: Learning Center, Exam Syllabus, PYQ Center, Quiz Center. | H11: Site says "500+ exams"; the catalogue holds more. Reconcile before quoting a number. Only feature exams with content live.
A12: 8 | B12: 4 | C12: Prepare | D12: P3 Prepare to Win | E12: Train like it is your PT schedule | F12: Daily tasks, lessons and practice tests, planned like your PT routine. | G12: Workflow step 3 (Training Plan); Today Objective card. | H12: Content coverage varies by state and UT; show exams that are actually populated.
A13: 9 | B13: 5 | C13: Career Paths | D13: P4 Beyond Government | E13: Beyond government: the private sector path | F13: A managed route to private-sector roles: a verified service profile, opportunities screened by VeerNXT HR, and a simple "I am interested" or "Not for me". | G13: Private Sector module (home, profile, opportunities). | H13: WhatsApp notifications were still simulated at last status report; do not promise alerts.
A14: 10 | B14: 5 | C14: Career Paths | D14: P1 Your Skills, Translated | E14: A CV that speaks civilian | F14: Present your service experience in the terms employers use, with the CV Builder. | G14: CV Builder page. | H14: Check the live CV Builder features before describing them.
A15: 11 | B15: 6 | C15: Career Paths | D15: P5 Hire Veterans | E15: For employers: pre-verified veteran talent | F15: The Employer Portal lets employers post requirements and find pre-verified veteran candidates. | G15: Employer portal (onboarding, dashboard, post job, find candidates). | H15: Landing copy says employers contact candidates directly; the Private Sector module is deliberately HR-mediated. Align the wording first.
A16: 12 | B16: 6 | C16: Career Paths | D16: P5 Hire Veterans | E16: What a service record tells an employer | F16: Discipline, leadership and teamwork under pressure are demonstrated, not claimed. | G16: Brand voice; general editorial point. | H16: None - no statistics used.
... A20: 16 | B20: 8 | C20: Join | D20: P0 The Second Mission | E20: Start your second mission | F20: Build your profile free and see your best-fit exams and jobs. Available in nine Indian languages. | G20: Languages: English, Hindi, Tamil, Bengali, Marathi, Malayalam, Telugu, Gujarati, Kannada; free-to-start model. | H20: Confirm app-store availability ("coming soon" on landing) and the CTA link.

Sheet Pillars
A1: Content Pillars
A2: Nine pillars, each tied to a real part of the VeerNXT product. Item and post counts come from the Themes and Schedule sheets.
A4: Pillar | B4: What it covers | C4: Main audience | D4: Lead platforms | E4: Content items | F4: Posts
A5: P0 The Second Mission | B5: Brand story: who VeerNXT is, and the invitation to join. | C5: All | D5: Facebook, LinkedIn | E5: =COUNTIF(Themes!$D$5:$D$20,A5) -> 2 | F5: =COUNTIF(Schedule!$L$5:$L$68,A5) -> 8
A6: P1 Your Skills, Translated | B6: Career profiling: military trade, rank and education mapped to a civilian skill profile and Veer Score; CV Builder. | C6: ESM, serving personnel planning ahead | D6: LinkedIn, Instagram | E6: =COUNTIF(Themes!$D$5:$D$20,A6) -> 4 | F6: =COUNTIF(Schedule!$L$5:$L$68,A6) -> 16
A7: P2 Every Opportunity, One Place | B7: Job aggregation from 10+ portals; ESM quotas, relaxations and bonus marks highlighted; expired jobs removed daily. | C7: ESM job seekers | D7: X, Facebook | E7: =COUNTIF(Themes!$D$5:$D$20,A7) -> 2 | F7: =COUNTIF(Schedule!$L$5:$L$68,A7) -> 8
A8: P3 Prepare to Win | B8: Learning Center: syllabus, guides, precis, previous-year papers, mock tests and quizzes for central and state exams; daily training plan. | C8: ESM preparing for government exams | D8: Instagram, Facebook | E8: =COUNTIF(Themes!$D$5:$D$20,A8) -> 2 | F8: =COUNTIF(Schedule!$L$5:$L$68,A8) -> 8
A9: P4 Beyond Government | B9: Private Sector module: verified service profile, VeerNXT HR-mediated opportunities, "I am interested" or "Not for me" only. | C9: ESM seeking corporate roles | D9: LinkedIn | E9: =COUNTIF(Themes!$D$5:$D$20,A9) -> 1 | F9: =COUNTIF(Schedule!$L$5:$L$68,A9) -> 4
A10: P5 Hire Veterans | B10: Employer Portal: pre-verified veteran talent, requirement posting; the value of service experience at work. | C10: Employers, HR leaders | D10: LinkedIn, X | E10: =COUNTIF(Themes!$D$5:$D$20,A10) -> 2 | F10: =COUNTIF(Schedule!$L$5:$L$68,A10) -> 8
A11: P6 Secure Your Future | B11: Financial guidance: calculators (SIP, step-up SIP, cost of delay, emergency fund, retirement), fixed deposits, mutual funds, insurance basics. | C11: ESM with separation corpus, families | D11: Facebook, Instagram | E11: =COUNTIF(Themes!$D$5:$D$20,A11) -> 1 | F11: =COUNTIF(Schedule!$L$5:$L$68,A11) -> 4
A12: P7 Stand By You | B12: Legal Aid Cell: guided intake for service, pension and family matters; coordinator connects to a legal professional. Not legal advice. | C12: ESM, families, dependants | D12: Facebook, LinkedIn | E12: =COUNTIF(Themes!$D$5:$D$20,A12) -> 1 | F12: =COUNTIF(Schedule!$L$5:$L$68,A12) -> 4
A13: P8 Stronger Together | B13: Community and network, mentors, peer support, rewards points; app available in 9 Indian languages. | C13: ESM, families, mentors | D13: Facebook, Instagram | E13: =COUNTIF(Themes!$D$5:$D$20,A13) -> 1 | F13: =COUNTIF(Schedule!$L$5:$L$68,A13) -> 4
A14: Total | E14: =SUM(E5:E13) -> 16 | F14: =SUM(F5:F13) -> 64
A16: Platform voice: LinkedIn = editorial and insight; X = short and sharp; Instagram = visual and warm; Facebook = conversational and community.

Sheet Schedule
A1: Campaign Schedule
A2: 8 weeks, 2 content items per week. Each item is published on all four platforms, staggered across the week (no daily posting). Times are IST. Themes and pillars come from the Themes sheet (change them there).
A4: Post # | B4: Week | C4: Content item # | D4: Theme | E4: Platform | F4: Format | G4: Date | H4: Day | I4: Time (IST) | J4: Day offset (Mon = 0) | K4: Status | L4: Pillar | M4: Phase
A5: 1 | B5: 1 | C5: 1 | D5: =INDEX(Themes!$E$5:$E$20,MATCH(C5,Themes!$A$5:$A$20,0)) -> Your second mission begins here | E5: LinkedIn | F5: Editorial post + image | G5: =Assumptions!$B$4+(B5-1)*7+J5 -> 46308 | H5: =TEXT(G5,"ddd") -> Tue | I5: 0.39583333 | J5: 1 | K5: Proposed | L5: =INDEX(Themes!$D$5:$D$20,MATCH(C5,Themes!$A$5:$A$20,0)) -> P0 The Second Mission | M5: =INDEX(Themes!$C$5:$C$20,MATCH(C5,Themes!$A$5:$A$20,0)) -> Awareness
A6: 2 | B6: 1 | C6: 1 | D6: =INDEX(Themes!$E$5:$E$20,MATCH(C6,Themes!$A$5:$A$20,0)) -> Your second mission begins here | E6: X | F6: Short post + image | G6: =Assumptions!$B$4+(B6-1)*7+J6 -> 46308 | H6: =TEXT(G6,"ddd") -> Tue | I6: 0.41666667 | J6: 1 | K6: Proposed | L6: =INDEX(Themes!$D$5:$D$20,MATCH(C6,Themes!$A$5:$A$20,0)) -> P0 The Second Mission | M6: =INDEX(Themes!$C$5:$C$20,MATCH(C6,Themes!$A$5:$A$20,0)) -> Awareness
A7: 3 | B7: 1 | C7: 1 | D7: =INDEX(Themes!$E$5:$E$20,MATCH(C7,Themes!$A$5:$A$20,0)) -> Your second mission begins here | E7: Facebook | F7: Community post + image | G7: =Assumptions!$B$4+(B7-1)*7+J7 -> 46309 | H7: =TEXT(G7,"ddd") -> Wed | I7: 0.79166667 | J7: 2 | K7: Proposed | L7: =INDEX(Themes!$D$5:$D$20,MATCH(C7,Themes!$A$5:$A$20,0)) -> P0 The Second Mission | M7: =INDEX(Themes!$C$5:$C$20,MATCH(C7,Themes!$A$5:$A$20,0)) -> Awareness
A8: 4 | B8: 1 | C8: 1 | D8: =INDEX(Themes!$E$5:$E$20,MATCH(C8,Themes!$A$5:$A$20,0)) -> Your second mission begins here | E8: Instagram | F8: Image post + caption | G8: =Assumptions!$B$4+(B8-1)*7+J8 -> 46310 | H8: =TEXT(G8,"ddd") -> Thu | I8: 0.75 | J8: 3 | K8: Proposed | L8: =INDEX(Themes!$D$5:$D$20,MATCH(C8,Themes!$A$5:$A$20,0)) -> P0 The Second Mission | M8: =INDEX(Themes!$C$5:$C$20,MATCH(C8,Themes!$A$5:$A$20,0)) -> Awareness
A9: 5 | B9: 1 | C9: 2 | D9: =INDEX(Themes!$E$5:$E$20,MATCH(C9,Themes!$A$5:$A$20,0)) -> Your service skills are civilian skills | E9: X | F9: Short post + image | G9: =Assumptions!$B$4+(B9-1)*7+J9 -> 46311 | H9: =TEXT(G9,"ddd") -> Fri | I9: 0.41666667 | J9: 4 | K9: Proposed | L9: =INDEX(Themes!$D$5:$D$20,MATCH(C9,Themes!$A$5:$A$20,0)) -> P1 Your Skills, Translated | M9: =INDEX(Themes!$C$5:$C$20,MATCH(C9,Themes!$A$5:$A$20,0)) -> Awareness
A10: 6 | B10: 1 | C10: 2 | D10: =INDEX(Themes!$E$5:$E$20,MATCH(C10,Themes!$A$5:$A$20,0)) -> Your service skills are civilian skills | E10: LinkedIn | F10: Editorial post + image | G10: =Assumptions!$B$4+(B10-1)*7+J10 -> 46311 | H10: =TEXT(G10,"ddd") -> Fri | I10: 0.52083333 | J10: 4 | K10: Proposed | L10: =INDEX(Themes!$D$5:$D$20,MATCH(C10,Themes!$A$5:$A$20,0)) -> P1 Your Skills, Translated | M10: =INDEX(Themes!$C$5:$C$20,MATCH(C10,Themes!$A$5:$A$20,0)) -> Awareness
A11: 7 | B11: 1 | C11: 2 | D11: =INDEX(Themes!$E$5:$E$20,MATCH(C11,Themes!$A$5:$A$20,0)) -> Your service skills are civilian skills | E11: Instagram | F11: Image post + caption | G11: =Assumptions!$B$4+(B11-1)*7+J11 -> 46312 | H11: =TEXT(G11,"ddd") -> Sat | I11: 0.75 | J11: 5 | K11: Proposed | L11: =INDEX(Themes!$D$5:$D$20,MATCH(C11,Themes!$A$5:$A$20,0)) -> P1 Your Skills, Translated | M11: =INDEX(Themes!$C$5:$C$20,MATCH(C11,Themes!$A$5:$A$20,0)) -> Awareness
A12: 8 | B12: 1 | C12: 2 | D12: =INDEX(Themes!$E$5:$E$20,MATCH(C12,Themes!$A$5:$A$20,0)) -> Your service skills are civilian skills | E12: Facebook | F12: Community post + image | G12: =Assumptions!$B$4+(B12-1)*7+J12 -> 46312 | H12: =TEXT(G12,"ddd") -> Sat | I12: 0.79166667 | J12: 5 | K12: Proposed | L12: =INDEX(Themes!$D$5:$D$20,MATCH(C12,Themes!$A$5:$A$20,0)) -> P1 Your Skills, Translated | M12: =INDEX(Themes!$C$5:$C$20,MATCH(C12,Themes!$A$5:$A$20,0)) -> Awareness
A13: 9 | B13: 2 | C13: 3 | D13: =INDEX(Themes!$E$5:$E$20,MATCH(C13,Themes!$A$5:$A$20,0)) -> Thirty seconds to your profile | E13: LinkedIn | F13: Editorial post + image | G13: =Assumptions!$B$4+(B13-1)*7+J13 -> 46315 | H13: =TEXT(G13,"ddd") -> Tue | I13: 0.39583333 | J13: 1 | K13: Proposed | L13: =INDEX(Themes!$D$5:$D$20,MATCH(C13,Themes!$A$5:$A$20,0)) -> P1 Your Skills, Translated | M13: =INDEX(Themes!$C$5:$C$20,MATCH(C13,Themes!$A$5:$A$20,0)) -> Discover
A14: 10 | B14: 2 | C14: 3 | D14: =INDEX(Themes!$E$5:$E$20,MATCH(C14,Themes!$A$5:$A$20,0)) -> Thirty seconds to your profile | E14: X | F14: Short post + image | G14: =Assumptions!$B$4+(B14-1)*7+J14 -> 46315 | H14: =TEXT(G14,"ddd") -> Tue | I14: 0.41666667 | J14: 1 | K14: Proposed | L14: =INDEX(Themes!$D$5:$D$20,MATCH(C14,Themes!$A$5:$A$20,0)) -> P1 Your Skills, Translated | M14: =INDEX(Themes!$C$5:$C$20,MATCH(C14,Themes!$A$5:$A$20,0)) -> Discover
A15: 11 | B15: 2 | C15: 3 | D15: =INDEX(Themes!$E$5:$E$20,MATCH(C15,Themes!$A$5:$A$20,0)) -> Thirty seconds to your profile | E15: Facebook | F15: Community post + image | G15: =Assumptions!$B$4+(B15-1)*7+J15 -> 46316 | H15: =TEXT(G15,"ddd") -> Wed | I15: 0.79166667 | J15: 2 | K15: Proposed | L15: =INDEX(Themes!$D$5:$D$20,MATCH(C15,Themes!$A$5:$A$20,0)) -> P1 Your Skills, Translated | M15: =INDEX(Themes!$C$5:$C$20,MATCH(C15,Themes!$A$5:$A$20,0)) -> Discover
A16: 12 | B16: 2 | C16: 3 | D16: =INDEX(Themes!$E$5:$E$20,MATCH(C16,Themes!$A$5:$A$20,0)) -> Thirty seconds to your profile | E16: Instagram | F16: Image post + caption | G16: =Assumptions!$B$4+(B16-1)*7+J16 -> 46317 | H16: =TEXT(G16,"ddd") -> Thu | I16: 0.75 | J16: 3 | K16: Proposed | L16: =INDEX(Themes!$D$5:$D$20,MATCH(C16,Themes!$A$5:$A$20,0)) -> P1 Your Skills, Translated | M16: =INDEX(Themes!$C$5:$C$20,MATCH(C16,Themes!$A$5:$A$20,0)) -> Discover
... A68: 64 | B68: 8 | C68: 16 | D68: =INDEX(Themes!$E$5:$E$20,MATCH(C68,Themes!$A$5:$A$20,0)) -> Start your second mission | E68: Facebook | F68: Community post + image | G68: =Assumptions!$B$4+(B68-1)*7+J68 -> 46361 | H68: =TEXT(G68,"ddd") -> Sat | I68: 0.79166667 | J68: 5 | K68: Proposed | L68: =INDEX(Themes!$D$5:$D$20,MATCH(C68,Themes!$A$5:$A$20,0)) -> P0 The Second Mission | M68: =INDEX(Themes!$C$5:$C$20,MATCH(C68,Themes!$A$5:$A$20,0)) -> Join

Sheet Cadence
A1: Posting Cadence
A2: Posts per platform per week, counted from the Schedule sheet.
A4: Platform | B4: Wk 1 | C4: Wk 2 | D4: Wk 3 | E4: Wk 4 | F4: Wk 5 | G4: Wk 6 | H4: Wk 7 | I4: Wk 8 | J4: Total | K4: Per week
A5: LinkedIn | B5: =COUNTIFS(Schedule!$E$5:$E$68,$A5,Schedule!$B$5:$B$68,1) -> 2 | C5: =COUNTIFS(Schedule!$E$5:$E$68,$A5,Schedule!$B$5:$B$68,2) -> 2 | D5: =COUNTIFS(Schedule!$E$5:$E$68,$A5,Schedule!$B$5:$B$68,3) -> 2 | E5: =COUNTIFS(Schedule!$E$5:$E$68,$A5,Schedule!$B$5:$B$68,4) -> 2 | F5: =COUNTIFS(Schedule!$E$5:$E$68,$A5,Schedule!$B$5:$B$68,5) -> 2 | G5: =COUNTIFS(Schedule!$E$5:$E$68,$A5,Schedule!$B$5:$B$68,6) -> 2 | H5: =COUNTIFS(Schedule!$E$5:$E$68,$A5,Schedule!$B$5:$B$68,7) -> 2 | I5: =COUNTIFS(Schedule!$E$5:$E$68,$A5,Schedule!$B$5:$B$68,8) -> 2 | J5: =SUM(B5:I5) -> 16 | K5: =J5/MAX(Schedule!$B$5:$B$68) -> 2
A6: X | B6: =COUNTIFS(Schedule!$E$5:$E$68,$A6,Schedule!$B$5:$B$68,1) -> 2 | C6: =COUNTIFS(Schedule!$E$5:$E$68,$A6,Schedule!$B$5:$B$68,2) -> 2 | D6: =COUNTIFS(Schedule!$E$5:$E$68,$A6,Schedule!$B$5:$B$68,3) -> 2 | E6: =COUNTIFS(Schedule!$E$5:$E$68,$A6,Schedule!$B$5:$B$68,4) -> 2 | F6: =COUNTIFS(Schedule!$E$5:$E$68,$A6,Schedule!$B$5:$B$68,5) -> 2 | G6: =COUNTIFS(Schedule!$E$5:$E$68,$A6,Schedule!$B$5:$B$68,6) -> 2 | H6: =COUNTIFS(Schedule!$E$5:$E$68,$A6,Schedule!$B$5:$B$68,7) -> 2 | I6: =COUNTIFS(Schedule!$E$5:$E$68,$A6,Schedule!$B$5:$B$68,8) -> 2 | J6: =SUM(B6:I6) -> 16 | K6: =J6/MAX(Schedule!$B$5:$B$68) -> 2
A7: Instagram | B7: =COUNTIFS(Schedule!$E$5:$E$68,$A7,Schedule!$B$5:$B$68,1) -> 2 | C7: =COUNTIFS(Schedule!$E$5:$E$68,$A7,Schedule!$B$5:$B$68,2) -> 2 | D7: =COUNTIFS(Schedule!$E$5:$E$68,$A7,Schedule!$B$5:$B$68,3) -> 2 | E7: =COUNTIFS(Schedule!$E$5:$E$68,$A7,Schedule!$B$5:$B$68,4) -> 2 | F7: =COUNTIFS(Schedule!$E$5:$E$68,$A7,Schedule!$B$5:$B$68,5) -> 2 | G7: =COUNTIFS(Schedule!$E$5:$E$68,$A7,Schedule!$B$5:$B$68,6) -> 2 | H7: =COUNTIFS(Schedule!$E$5:$E$68,$A7,Schedule!$B$5:$B$68,7) -> 2 | I7: =COUNTIFS(Schedule!$E$5:$E$68,$A7,Schedule!$B$5:$B$68,8) -> 2 | J7: =SUM(B7:I7) -> 16 | K7: =J7/MAX(Schedule!$B$5:$B$68) -> 2
A8: Facebook | B8: =COUNTIFS(Schedule!$E$5:$E$68,$A8,Schedule!$B$5:$B$68,1) -> 2 | C8: =COUNTIFS(Schedule!$E$5:$E$68,$A8,Schedule!$B$5:$B$68,2) -> 2 | D8: =COUNTIFS(Schedule!$E$5:$E$68,$A8,Schedule!$B$5:$B$68,3) -> 2 | E8: =COUNTIFS(Schedule!$E$5:$E$68,$A8,Schedule!$B$5:$B$68,4) -> 2 | F8: =COUNTIFS(Schedule!$E$5:$E$68,$A8,Schedule!$B$5:$B$68,5) -> 2 | G8: =COUNTIFS(Schedule!$E$5:$E$68,$A8,Schedule!$B$5:$B$68,6) -> 2 | H8: =COUNTIFS(Schedule!$E$5:$E$68,$A8,Schedule!$B$5:$B$68,7) -> 2 | I8: =COUNTIFS(Schedule!$E$5:$E$68,$A8,Schedule!$B$5:$B$68,8) -> 2 | J8: =SUM(B8:I8) -> 16 | K8: =J8/MAX(Schedule!$B$5:$B$68) -> 2
A9: All platforms | B9: =SUM(B5:B8) -> 8 | C9: =SUM(C5:C8) -> 8 | D9: =SUM(D5:D8) -> 8 | E9: =SUM(E5:E8) -> 8 | F9: =SUM(F5:F8) -> 8 | G9: =SUM(G5:G8) -> 8 | H9: =SUM(H5:H8) -> 8 | I9: =SUM(I5:I8) -> 8 | J9: =SUM(J5:J8) -> 64 | K9: =J9/MAX(Schedule!$B$5:$B$68) -> 8
A11: Comparison with posting daily on every platform
A12: Posts if daily on all 4 platforms | B12: =4*7*MAX(Schedule!$B$5:$B$68) -> 224
A13: Posts in this plan | B13: =J9 -> 64
A14: Reduction vs daily | B14: =1-B13/B12 -> 0.71428571

Sheet Costing
A1: Campaign Costing
A2: AI content generation only (OpenAI API). Low / Expected / High cases. USD and INR. All figures are estimates - see Assumptions.
A4: Line | B4: Low (USD) | C4: Expected (USD) | D4: High (USD) | E4: Low (INR) | F4: Expected (INR) | G4: High (INR)
A5: Content items to generate | B5: =MAX(Schedule!$C$5:$C$68) -> 16 | C5: =MAX(Schedule!$C$5:$C$68) -> 16 | D5: =MAX(Schedule!$C$5:$C$68) -> 16
A6: Posts to publish | B6: =COUNTA(Schedule!$E$5:$E$68) -> 64 | C6: =COUNTA(Schedule!$E$5:$E$68) -> 64 | D6: =COUNTA(Schedule!$E$5:$E$68) -> 64
A8: Text generation (4 platforms per item) | B8: =B$5*Assumptions!B$11 -> 0.192 | C8: =C$5*Assumptions!C$11 -> 0.24 | D8: =D$5*Assumptions!D$11 -> 0.32 | E8: =B8*Assumptions!$B$5 -> 18.528 | F8: =C8*Assumptions!$B$5 -> 23.16 | G8: =D8*Assumptions!$B$5 -> 30.88
A9: Image generation (1 image per item) | B9: =B$5*Assumptions!B$12 -> 0.208 | C9: =C$5*Assumptions!C$12 -> 0.28 | D9: =D$5*Assumptions!D$12 -> 0.48 | E9: =B9*Assumptions!$B$5 -> 20.072 | F9: =C9*Assumptions!$B$5 -> 27.02 | G9: =D9*Assumptions!$B$5 -> 46.32
A10: Refinement edits by the team | B10: =B$5*Assumptions!B$13*Assumptions!B$14 -> 0.064 | C10: =C$5*Assumptions!C$13*Assumptions!C$14 -> 0.16 | D10: =D$5*Assumptions!D$13*Assumptions!D$14 -> 0.512 | E10: =B10*Assumptions!$B$5 -> 6.176 | F10: =C10*Assumptions!$B$5 -> 15.44 | G10: =D10*Assumptions!$B$5 -> 49.408
A11: Regeneration allowance after review | B11: =B$5*Assumptions!B$15*(Assumptions!B$11+Assumptions!B$12) -> 0.04 | C11: =C$5*Assumptions!C$15*(Assumptions!C$11+Assumptions!C$12) -> 0.13 | D11: =D$5*Assumptions!D$15*(Assumptions!D$11+Assumptions!D$12) -> 0.4 | E11: =B11*Assumptions!$B$5 -> 3.86 | F11: =C11*Assumptions!$B$5 -> 12.545 | G11: =D11*Assumptions!$B$5 -> 38.6
A12: AI generation subtotal | B12: =SUM(B8:B11) -> 0.504 | C12: =SUM(C8:C11) -> 0.81 | D12: =SUM(D8:D11) -> 1.712 | E12: =B12*Assumptions!$B$5 -> 48.636 | F12: =C12*Assumptions!$B$5 -> 78.165 | G12: =D12*Assumptions!$B$5 -> 165.208
A13: Hosting / third-party tools (not included unless entered) | B13: =E13/Assumptions!$B$5 -> 0 | C13: =F13/Assumptions!$B$5 -> 0 | D13: =G13/Assumptions!$B$5 -> 0 | E13: =Assumptions!$B$6*Assumptions!$B$7 -> 0 | F13: =Assumptions!$B$6*Assumptions!$B$7 -> 0 | G13: =Assumptions!$B$6*Assumptions!$B$7 -> 0
A14: TOTAL CAMPAIGN COST | B14: =B12+B13 -> 0.504 | C14: =C12+C13 -> 0.81 | D14: =D12+D13 -> 1.712 | E14: =E12+E13 -> 48.636 | F14: =F12+F13 -> 78.165 | G14: =G12+G13 -> 165.208
A16: Cost per content item | B16: =B14/B5 -> 0.0315 | C16: =C14/C5 -> 0.050625 | D16: =D14/D5 -> 0.107 | E16: =E14/B5 -> 3.03975 | F16: =F14/C5 -> 4.8853125 | G16: =G14/D5 -> 10.3255
A17: Cost per post | B17: =B14/B6 -> 0.007875 | C17: =C14/C6 -> 0.01265625 | D17: =D14/D6 -> 0.02675 | E17: =E14/B6 -> 0.7599375 | F17: =F14/C6 -> 1.2213281 | G17: =G14/D6 -> 2.581375
A19: Notes
A20: Publishing is not costed: the app currently publishes via Mock/Manual providers (no per-post fee). Native LinkedIn / X / Meta API integration and any scheduler such as Buffer are not yet priced.
A21: Excluded: paid promotion / ad spend, staff time for review and approval, GST, bank foreign-transaction fees, and hosting unless entered in Assumptions.
A22: Rates and token counts are estimates from public price pages and assumed token volumes; check the OpenAI usage dashboard for actual spend.

Sheet Assumptions
A1: Assumptions & Inputs
A2: Blue cells are inputs - change them and every sheet recalculates. Yellow = key assumptions to confirm.
A3: General
A4: Campaign start date (a Monday) | B4: 46307 | E4: Proposed. Change to the approved launch date.
A5: USD to INR exchange rate | B5: 96.5 | E5: Approx. rate at 30 Sep 2026 from a web search (pluang.com currency converter); not a live rate. Update before final approval.
A6: Hosting / third-party tools (INR per month) | B6: 0 | E6: NOT INCLUDED - to confirm (e.g. Vercel, Supabase, Buffer). Enter monthly amount if applicable.
A7: Campaign length (months, derived) | B7: =MAX(Schedule!B5:B68)/(52/12) -> 1.8461538
A9: Per-unit cost inputs
A10: Item | B10: Low | C10: Expected | D10: High | E10: Basis
A11: Text generation, USD per content item (all 4 platforms, gpt-4o) | B11: 0.012 | C11: 0.015 | D11: 0.02 | E11: gpt-4o at $2.50/1M input and $10/1M output tokens (analyticsvidhya.com). Assumes ~1,000 tokens in, ~1,200 out. Estimate.
A12: Image, USD per image (gpt-image-2.5-flare, medium quality) | B12: 0.013 | C12: 0.0175 | D12: 0.03 | E12: Flare: $30/1M image-output tokens; ~439 tokens for 1024x1024 medium = ~$0.013 (openrouter.ai). Landscape 1536x1024 costs more. Estimate.
A13: Refinement call, USD each (short gpt-4o edit) | B13: 0.004 | C13: 0.005 | D13: 0.008 | E13: Estimate: short prompt and single-post response.
A14: Refinements per content item (count) | B14: 1 | C14: 2 | D14: 4 | E14: Editor "shorten / hook / CTA" style edits by the team. Assumption.
A15: Regeneration allowance (% of items re-generated) | B15: 0.1 | C15: 0.25 | D15: 0.5 | E15: Items re-run in full (text + image) after review feedback. Assumption.
